conrad/__init__.py
conrad/__main__.py
conrad/__version__.py
conrad/cli.py
conrad/db.py
conrad/models.py
conrad/schema.py
conrad/utils.py
crawlers/__init__.py
crawlers/base.py
crawlers/confs_tech/__init__.py
crawlers/confs_tech/confs_tech_crawler.py
crawlers/italy/__init__.py
crawlers/italy/italy_crawler.py
crawlers/papercall/__init__.py
crawlers/papercall/papercall_crawler.py
crawlers/pycon/__init__.py
crawlers/pycon/pycon_crawler.py
crawlers/pydata/__init__.py
crawlers/pydata/pydata_crawler.py
crawlers/python/__init__.py
crawlers/python/python_crawler.py
conference_radar-0.10.2.dist-info/LICENSE
conference_radar-0.10.2.dist-info/METADATA
conference_radar-0.10.2.dist-info/WHEEL
conference_radar-0.10.2.dist-info/entry_points.txt
conference_radar-0.10.2.dist-info/top_level.txt
conference_radar-0.10.2.dist-info/RECORD
