Metadata-Version: 2.1
Name: conference-radar
Version: 0.10.2
Summary: Track conferences and meetups on your terminal.
Home-page: https://github.com/vinayak-mehta/conrad
Author: Vinayak Mehta
Author-email: vmehta94@gmail.com
License: Apache 2.0
Classifier: License :: OSI Approved :: Apache Software License
Classifier: Programming Language :: Python :: 3.6
Classifier: Programming Language :: Python :: 3.7
Classifier: Programming Language :: Python :: 3.8
Classifier: Programming Language :: Python :: 3.9
License-File: LICENSE
Requires-Dist: Click>=7.0
Requires-Dist: cli-helpers>=1.2.1
Requires-Dist: colorama>=0.4.1
Requires-Dist: geopy>=2.0.0
Requires-Dist: requests>=2.22.0
Requires-Dist: rich>=10.6.0
Requires-Dist: SQLAlchemy>=1.3.10
Requires-Dist: textdistance>=4.1.5
Provides-Extra: all
Requires-Dist: beautifulsoup4>=4.8.1; extra == "all"
Requires-Dist: Cerberus>=1.3.2; extra == "all"
Requires-Dist: dateparser>=0.7.2; extra == "all"
Requires-Dist: GitPython>=3.1.18; extra == "all"
Requires-Dist: google-api-python-client>=1.10.0; extra == "all"
Requires-Dist: pandas>=0.25.2; extra == "all"
Requires-Dist: pyOpenSSL>=19.0.0; extra == "all"
Requires-Dist: requests>=2.22.0; extra == "all"
Requires-Dist: textdistance>=4.1.5; extra == "all"
Requires-Dist: Sphinx>=2.2.1; extra == "all"
Requires-Dist: pytest>=3.8.0; extra == "all"
Requires-Dist: Click>=7.0; extra == "all"
Requires-Dist: cli-helpers>=1.2.1; extra == "all"
Requires-Dist: colorama>=0.4.1; extra == "all"
Requires-Dist: geopy>=2.0.0; extra == "all"
Requires-Dist: requests>=2.22.0; extra == "all"
Requires-Dist: rich>=10.6.0; extra == "all"
Requires-Dist: SQLAlchemy>=1.3.10; extra == "all"
Requires-Dist: textdistance>=4.1.5; extra == "all"
Provides-Extra: dev
Requires-Dist: Sphinx>=2.2.1; extra == "dev"
Requires-Dist: pytest>=3.8.0; extra == "dev"
Requires-Dist: Click>=7.0; extra == "dev"
Requires-Dist: cli-helpers>=1.2.1; extra == "dev"
Requires-Dist: colorama>=0.4.1; extra == "dev"
Requires-Dist: geopy>=2.0.0; extra == "dev"
Requires-Dist: requests>=2.22.0; extra == "dev"
Requires-Dist: rich>=10.6.0; extra == "dev"
Requires-Dist: SQLAlchemy>=1.3.10; extra == "dev"
Requires-Dist: textdistance>=4.1.5; extra == "dev"
